njmls.py
njmls-0.0.3.dist-info/LICENSE
njmls-0.0.3.dist-info/METADATA
njmls-0.0.3.dist-info/WHEEL
njmls-0.0.3.dist-info/top_level.txt
njmls-0.0.3.dist-info/RECORD
